{
    "haskell-nix": {
        "branch": "master",
        "description": "Alternative Haskell Infrastructure for Nixpkgs",
        "homepage": "https://input-output-hk.github.io/haskell.nix",
        "owner": "input-output-hk",
        "repo": "haskell.nix",
        "rev": "bc471e5235246ca015cd6755adfe1feaa8761498",
        "sha256": "084jibcra9zj2nd9zxjf9lkjxkz2rx3f4prxa5bfz4aq628v39na",
        "type": "tarball",
        "url": "https://github.com/input-output-hk/haskell.nix/archive/bc471e5235246ca015cd6755adfe1feaa8761498.tar.gz",
        "url_template": "https://github.com/<owner>/<repo>/archive/<rev>.tar.gz"
    },
    "hs-nix-tools": {
        "branch": "master",
        "description": null,
        "homepage": null,
        "owner": "TerrorJack",
        "repo": "hs-nix-tools",
        "rev": "bc5ca48ba3680986ac7d6f63de0cabded9fb01ba",
        "sha256": "1bh05msqfhl7hrr1pspgvi0gfazm8bx8cy86zp6n5wni6l1r90s7",
        "type": "tarball",
        "url": "https://github.com/TerrorJack/hs-nix-tools/archive/bc5ca48ba3680986ac7d6f63de0cabded9fb01ba.tar.gz",
        "url_template": "https://github.com/<owner>/<repo>/archive/<rev>.tar.gz"
    }
}
