{
    "haskell-nix": {
        "branch": "master",
        "description": "Alternative Haskell Infrastructure for Nixpkgs",
        "homepage": "https://input-output-hk.github.io/haskell.nix",
        "owner": "TerrorJack",
        "repo": "haskell.nix",
        "rev": "edda3f1f63afd4ca599304fdee5a79ec3ddd16e9",
        "sha256": "08r5g601q71kl60rzds0mxsdij6h367ijxsp8n7d5z50ymyvh3mh",
        "type": "tarball",
        "url": "https://github.com/TerrorJack/haskell.nix/archive/edda3f1f63afd4ca599304fdee5a79ec3ddd16e9.tar.gz",
        "url_template": "https://github.com/<owner>/<repo>/archive/<rev>.tar.gz"
    },
    "hs-nix-tools": {
        "branch": "master",
        "description": null,
        "homepage": null,
        "owner": "TerrorJack",
        "repo": "hs-nix-tools",
        "rev": "46b072e48d97e56e401becce9ff3a57fbe92f317",
        "sha256": "1mg9g6623hsxk7xvsgc2raz99i3nymxgz8k104yljycrdxs0l7fm",
        "type": "tarball",
        "url": "https://github.com/TerrorJack/hs-nix-tools/archive/46b072e48d97e56e401becce9ff3a57fbe92f317.tar.gz",
        "url_template": "https://github.com/<owner>/<repo>/archive/<rev>.tar.gz"
    }
}
